spg/__init__.py
spg/agent/__init__.py
spg/agent/agent.py
spg/agent/agents.py
spg/agent/device.py
spg/agent/communicator/__init__.py
spg/agent/communicator/communicator.py
spg/agent/controller/__init__.py
spg/agent/controller/controller.py
spg/agent/interactor/__init__.py
spg/agent/interactor/grasper.py
spg/agent/interactor/interactor.py
spg/agent/part/__init__.py
spg/agent/part/part.py
spg/agent/part/parts.py
spg/agent/sensor/__init__.py
spg/agent/sensor/aerial.py
spg/agent/sensor/area.py
spg/agent/sensor/internal.py
spg/agent/sensor/ray.py
spg/agent/sensor/sensor.py
spg/agent/sensor/shaders/aerial_fragment.glsl
spg/agent/sensor/shaders/aerial_vertex.glsl
spg/agent/sensor/shaders/color_compute.glsl
spg/agent/sensor/shaders/id_compute.glsl
spg/element/__init__.py
spg/element/ball.py
spg/element/chest.py
spg/element/diamond.py
spg/element/disabler.py
spg/element/element.py
spg/element/wall.py
spg/entity/__init__.py
spg/entity/embodied.py
spg/entity/entity.py
spg/entity/interactive.py
spg/entity/physical.py
spg/entity/spawner.py
spg/entity/timer.py
spg/playground/__init__.py
spg/playground/checkpoint.py
spg/playground/collision_handlers.py
spg/playground/playground.py
spg/playground/room.py
spg/playground/playgrounds/__init__.py
spg/resources/__init__.py
spg/resources/platformer/License.txt
spg/resources/platformer/items/diamond_blue.png
spg/resources/platformer/items/diamond_empty.png
spg/resources/platformer/items/diamond_green.png
spg/resources/platformer/items/diamond_red.png
spg/resources/platformer/items/diamond_yellow.png
spg/resources/platformer/items/gem_blue.png
spg/resources/platformer/items/gem_empty.png
spg/resources/platformer/items/gem_green.png
spg/resources/platformer/items/gem_red.png
spg/resources/platformer/items/gem_yellow.png
spg/resources/platformer/items/heart_empty.png
spg/resources/platformer/items/heart_full.png
spg/resources/platformer/items/heart_half.png
spg/resources/platformer/items/key_blue.png
spg-0.1.9.dist-info/LICENSE
spg-0.1.9.dist-info/METADATA
spg-0.1.9.dist-info/WHEEL
spg-0.1.9.dist-info/top_level.txt
spg-0.1.9.dist-info/RECORD
