Metadata-Version: 2.1
Name: spg
Version: 0.1.9
Summary: Simulator for Reinforcement Learning
Author: Michael Garcia Ortiz
Author-email: michael.garcia.ortiz@gmail.com
License-File: LICENSE
Requires-Dist: pyyaml
Requires-Dist: pymunk (>=6.0.0)
Requires-Dist: numpy
Requires-Dist: scikit-image
Requires-Dist: pillow
Requires-Dist: pytest
Requires-Dist: matplotlib
Requires-Dist: gym
Requires-Dist: arcade
Requires-Dist: tripy
Requires-Dist: tqdm
